{"name":"build-javascript","namedChunkGroups":{"app":{"name":"app","assets":[{"name":"webpack-runtime-898f14a5f19133f84d77.js","size":4774},{"name":"framework-a61283e45d8d5579f528.js","size":140777},{"name":"app-f954f4e43be26e5dcbb2.js","size":86213}],"filteredAssets":0,"assetsSize":231764,"filteredAuxiliaryAssets":3,"auxiliaryAssetsSize":739136},"component---src-pages-404-tsx":{"name":"component---src-pages-404-tsx","assets":[{"name":"component---src-pages-404-tsx-2565c74683aa24eef3aa.js","size":741}],"filteredAssets":0,"assetsSize":741,"filteredAuxiliaryAssets":1,"auxiliaryAssetsSize":1957},"component---src-pages-index-tsx":{"name":"component---src-pages-index-tsx","assets":[{"name":"styles.7b1b0856607710effab1.css","size":1855},{"name":"c16184b3-9390f51a6f0f0661dce6.js","size":1514},{"name":"2cca2479-67351648bcb3e8b47eb6.js","size":2876},{"name":"component---src-pages-index-tsx-b3b0ceb0de75e9de018e.js","size":75776}],"filteredAssets":0,"assetsSize":82021,"filteredAuxiliaryAssets":3,"auxiliaryAssetsSize":1780737}},"assetsByChunkName":{"app":["webpack-runtime-898f14a5f19133f84d77.js","framework-a61283e45d8d5579f528.js","app-f954f4e43be26e5dcbb2.js"],"component---src-pages-404-tsx":["component---src-pages-404-tsx-2565c74683aa24eef3aa.js"],"component---src-pages-index-tsx":["styles.7b1b0856607710effab1.css","c16184b3-9390f51a6f0f0661dce6.js","2cca2479-67351648bcb3e8b47eb6.js","component---src-pages-index-tsx-b3b0ceb0de75e9de018e.js"]},"childAssetsByChunkName":{}}